README
setup.py
django_digest/__init__.py
django_digest/decorators.py
django_digest/middleware.py
django_digest/models.py
django_digest/mysqltestsettings.py
django_digest/tests.py
django_digest/testsettings.py
django_digest/utils.py
django_digest.egg-info/PKG-INFO
django_digest.egg-info/SOURCES.txt
django_digest.egg-info/dependency_links.txt
django_digest.egg-info/not-zip-safe
django_digest.egg-info/top_level.txt
django_digest/backend/__init__.py
django_digest/backend/db.py
django_digest/backend/storage.py
django_digest/migrations/0001_initial.py
django_digest/migrations/0002_multiple_logins.py
django_digest/migrations/0003_require_login_field.py
django_digest/migrations/__init__.py
django_digest/test/__init__.py
django_digest/test/methods/__init__.py
django_digest/test/methods/basic.py
django_digest/test/methods/detect.py
django_digest/test/methods/digest.py