Metadata-Version: 1.0
Name: django-digest
Version: 1.12
Summary: An implementation of HTTP Digest Authentication for Django.
Home-page: http://bitbucket.org/akoha/django-digest/
Author: Akoha Inc.
Author-email: adminmail@akoha.com
License: UNKNOWN
Platform: UNKNOWN
Classifier: Development Status :: 5 - Production/Stable
Classifier: Environment :: Web Environment
Classifier: Framework :: Django
Classifier: License :: OSI Approved :: BSD License
Classifier: Operating System :: OS Independent
Classifier: Programming Language :: Python
Classifier: Topic :: Software Development :: Libraries :: Python Modules
